Metadata-Version: 1.1
Name: odooModule
Version: 0.1.6
Summary: Module for querying, modifying, deleting, and creating models in Odoo
Home-page: https://github.com/Little-Unicorn/Odoo.git
Author: bryan Brandley
Author-email: bbrandley@littleunicorn.com
License: UNKNOWN
Platform: UNKNOWN
Classifier: Development Status :: 1 - Planning
Classifier: Programming Language :: Python :: 2
Classifier: Programming Language :: Python :: 2.7
Classifier: Programming Language :: Python :: 3
Classifier: Programming Language :: Python :: 3.4
Classifier: Programming Language :: Python :: 3.9
